{
    "name": "R Dev Environment",
    "build": {
        "dockerfile": "../docker/Dockerfile"
    },
    "workspaceFolder": "/workspace",
    "mounts": [
        "source=${localWorkspaceFolder},target=/workspace,type=bind,consistency=cached"
    ],
    "extensions": [
        "Ikuyadeu.r",  // R extension for VSCode
        "ms-azuretools.vscode-docker",
        "ms-vscode-remote.remote-containers"
    ],
    "settings": {
        "r.rterm.linux": "/usr/local/bin/R",  // path to the R interpreter
        "r.lsp.path": "/usr/local/bin/R"  // Language server for R
    },
    "remoteUser": "root"
}
